[
    {
        "id": "2",
        "name": "₹500 Amazon E-Gift Card Instant Voucher",
        "color": "Default",
        "size": "Free Size",
        "storage": null,
        "selling_price": "1",
        "mrp": "500",
        "fetaures": "<img src=\".\/jacketimg\/AAAS.jpg\" style=\"max-width: 100%\"> <\/ div>",
        "img1": "https://cdn.grofers.com/cdn-cgi/image/f=auto,fit=scale-down,q=70,metadata=none,w=1080/da/cms-assets/cms/product/6feb5ac2-9e83-46c9-a358-03b77e6d3093.png",
        "img2": "https://cdn.grofers.com/cdn-cgi/image/f=auto,fit=scale-down,q=70,metadata=none,w=1080/da/cms-assets/cms/product/deb421f6-4c4d-4c65-9193-4be3a858c422.png",
        "img3": "https://cdn.grofers.com/cdn-cgi/image/f=auto,fit=scale-down,q=70,metadata=none,w=1080/da/cms-assets/cms/product/9de14f2c-b4be-4635-960c-3d863e472dac.png",
        "img4": "https://cdn.grofers.com/cdn-cgi/image/f=auto,fit=scale-down,q=70,metadata=none,w=1080/da/cms-assets/cms/product/6feb5ac2-9e83-46c9-a358-03b77e6d3093.png",
        "img5": "https://cdn.grofers.com/cdn-cgi/image/f=auto,fit=scale-down,q=70,metadata=none,w=1080/da/cms-assets/cms/product/6feb5ac2-9e83-46c9-a358-03b77e6d3093.png",
        "disp_order": 0,
        "from_csv": "1",
        "created_at": "2025-05-28 11:53:09",
        "md5_id": "d5344a477f277d79fb2174acff73343a",
        "verients": []
    },
    {
        "id": "4",
        "name": "₹500 Domino's E-Gift Card Instant Voucher",
        "color": "Default",
        "size": "Free Size",
        "storage": null,
        "selling_price": "1",
        "mrp": "500",
        "fetaures": "<img src=\".\/jacketimg\/AAAS.jpg\" style=\"max-width: 100%\"> <\/ div>",
        "img1": "https://cdn.grofers.com/cdn-cgi/image/f=auto,fit=scale-down,q=70,metadata=none,w=1080/da/cms-assets/cms/product/c1287695-eecb-41fe-8cfe-a8a50445e6a1.png",
        "img2": "https://cdn.grofers.com/cdn-cgi/image/f=auto,fit=scale-down,q=70,metadata=none,w=1080/da/cms-assets/cms/product/deb421f6-4c4d-4c65-9193-4be3a858c422.png",
        "img3": "https://cdn.grofers.com/cdn-cgi/image/f=auto,fit=scale-down,q=70,metadata=none,w=1080/da/cms-assets/cms/product/9de14f2c-b4be-4635-960c-3d863e472dac.png",
        "img4": "https://cdn.grofers.com/cdn-cgi/image/f=auto,fit=scale-down,q=70,metadata=none,w=1080/da/cms-assets/cms/product/c1287695-eecb-41fe-8cfe-a8a50445e6a1.png",
        "img5": "https://cdn.grofers.com/cdn-cgi/image/f=auto,fit=scale-down,q=70,metadata=none,w=1080/da/cms-assets/cms/product/c1287695-eecb-41fe-8cfe-a8a50445e6a1.png",
        "disp_order": 0,
        "from_csv": "1",
        "created_at": "2025-05-28 12:01:15",
        "md5_id": "a6a9f2e63a9968b3e723e77cbffccde0",
        "verients": []
    },
    {
        "id": "6",
        "name": "₹500 Nykaa E-Gift Card Instant Voucher",
        "color": "Default",
        "size": "Free Size",
        "storage": null,
        "selling_price": "1",
        "mrp": "500",
        "fetaures": "<img src=\".\/jacketimg\/AAAS.jpg\" style=\"max-width: 100%\"> <\/ div>",
        "img1": "https://cdn.grofers.com/cdn-cgi/image/f=auto,fit=scale-down,q=70,metadata=none,w=1080/da/cms-assets/cms/product/5624cce0-80d3-4218-b461-20e418431f28.png",
        "img2": "https://cdn.grofers.com/cdn-cgi/image/f=auto,fit=scale-down,q=70,metadata=none,w=1080/da/cms-assets/cms/product/deb421f6-4c4d-4c65-9193-4be3a858c422.png",
        "img3": "https://cdn.grofers.com/cdn-cgi/image/f=auto,fit=scale-down,q=70,metadata=none,w=1080/da/cms-assets/cms/product/9de14f2c-b4be-4635-960c-3d863e472dac.png",
        "img4": "https://cdn.grofers.com/cdn-cgi/image/f=auto,fit=scale-down,q=70,metadata=none,w=1080/da/cms-assets/cms/product/5624cce0-80d3-4218-b461-20e418431f28.png",
        "img5": "https://cdn.grofers.com/cdn-cgi/image/f=auto,fit=scale-down,q=70,metadata=none,w=1080/da/cms-assets/cms/product/5624cce0-80d3-4218-b461-20e418431f28.png",
        "disp_order": 0,
        "from_csv": "1",
        "created_at": "2025-05-28 12:30:33",
        "md5_id": "9aa54c11a25dd74acbc08a2ee92c590e",
        "verients": []
    },
        {
        "id": "7",
        "name": "₹500 Pizza Hut E-Gift Card Instant Voucher",
        "color": "Default",
        "size": "Free Size",
        "storage": null,
        "selling_price": "1",
        "mrp": "500",
        "fetaures": "<img src=\".\/jacketimg\/AAAS.jpg\" style=\"max-width: 100%\"> <\/ div>",
        "img1": "https://cdn.grofers.com/cdn-cgi/image/f=auto,fit=scale-down,q=70,metadata=none,w=1080/da/cms-assets/cms/product/9ecb6d05-7e3f-43fb-831f-f9c66e94460e.png",
        "img2": "https://cdn.grofers.com/cdn-cgi/image/f=auto,fit=scale-down,q=70,metadata=none,w=1080/da/cms-assets/cms/product/deb421f6-4c4d-4c65-9193-4be3a858c422.png",
        "img3": "https://cdn.grofers.com/cdn-cgi/image/f=auto,fit=scale-down,q=70,metadata=none,w=1080/da/cms-assets/cms/product/9de14f2c-b4be-4635-960c-3d863e472dac.png",
        "img4": "https://cdn.grofers.com/cdn-cgi/image/f=auto,fit=scale-down,q=70,metadata=none,w=1080/da/cms-assets/cms/product/9ecb6d05-7e3f-43fb-831f-f9c66e94460e.png",
        "img5": "https://cdn.grofers.com/cdn-cgi/image/f=auto,fit=scale-down,q=70,metadata=none,w=1080/da/cms-assets/cms/product/9ecb6d05-7e3f-43fb-831f-f9c66e94460e.png",
        "disp_order": 0,
        "from_csv": "1",
        "created_at": "2025-05-28 12:30:33",
        "md5_id": "9aa54c11a25dd74acbc08a2ee92c590e",
        "verients": []
    },
            {
        "id": "8",
        "name": "₹500 Kalyan Jewellers E-Gift Card Instant Voucher",
        "color": "Default",
        "size": "Free Size",
        "storage": null,
        "selling_price": "1",
        "mrp": "500",
        "fetaures": "<img src=\".\/jacketimg\/AAAS.jpg\" style=\"max-width: 100%\"> <\/ div>",
        "img1": "https://cdn.grofers.com/cdn-cgi/image/f=auto,fit=scale-down,q=70,metadata=none,w=1080/da/cms-assets/cms/product/fb430b3a-73d7-4df6-a73a-e018923f45bd.png",
        "img2": "https://cdn.grofers.com/cdn-cgi/image/f=auto,fit=scale-down,q=70,metadata=none,w=1080/da/cms-assets/cms/product/deb421f6-4c4d-4c65-9193-4be3a858c422.png",
        "img3": "https://cdn.grofers.com/cdn-cgi/image/f=auto,fit=scale-down,q=70,metadata=none,w=1080/da/cms-assets/cms/product/9de14f2c-b4be-4635-960c-3d863e472dac.png",
        "img4": "https://cdn.grofers.com/cdn-cgi/image/f=auto,fit=scale-down,q=70,metadata=none,w=1080/da/cms-assets/cms/product/fb430b3a-73d7-4df6-a73a-e018923f45bd.png",
        "img5": "https://cdn.grofers.com/cdn-cgi/image/f=auto,fit=scale-down,q=70,metadata=none,w=1080/da/cms-assets/cms/product/fb430b3a-73d7-4df6-a73a-e018923f45bd.png",
        "disp_order": 0,
        "from_csv": "1",
        "created_at": "2025-05-28 12:30:33",
        "md5_id": "9aa54c11a25dd74acbc08a2ee92c590e",
        "verients": []
    },
      {
        "id": "9",
        "name": "₹500 KFC E-Gift Card Instant Voucher",
        "color": "Default",
        "size": "Free Size",
        "storage": null,
        "selling_price": "1",
        "mrp": "500",
        "fetaures": "<img src=\".\/jacketimg\/AAAS.jpg\" style=\"max-width: 100%\"> <\/ div>",
        "img1": "https://cdn.grofers.com/cdn-cgi/image/f=auto,fit=scale-down,q=70,metadata=none,w=1080/da/cms-assets/cms/product/77746cb3-1468-4089-bad2-43b4557574df.png",
        "img2": "https://cdn.grofers.com/cdn-cgi/image/f=auto,fit=scale-down,q=70,metadata=none,w=1080/da/cms-assets/cms/product/deb421f6-4c4d-4c65-9193-4be3a858c422.png",
        "img3": "https://cdn.grofers.com/cdn-cgi/image/f=auto,fit=scale-down,q=70,metadata=none,w=1080/da/cms-assets/cms/product/9de14f2c-b4be-4635-960c-3d863e472dac.png",
        "img4": "https://cdn.grofers.com/cdn-cgi/image/f=auto,fit=scale-down,q=70,metadata=none,w=1080/da/cms-assets/cms/product/77746cb3-1468-4089-bad2-43b4557574df.png",
        "img5": "https://cdn.grofers.com/cdn-cgi/image/f=auto,fit=scale-down,q=70,metadata=none,w=1080/da/cms-assets/cms/product/77746cb3-1468-4089-bad2-43b4557574df.png",
        "disp_order": 0,
        "from_csv": "1",
        "created_at": "2025-05-28 12:30:33",
        "md5_id": "9aa54c11a25dd74acbc08a2ee92c590e",
        "verients": []
    },
      {
        "id": "10",
        "name": "₹500 Puma E-Gift Card Instant Voucher",
        "color": "Default",
        "size": "Free Size",
        "storage": null,
        "selling_price": "1",
        "mrp": "500",
        "fetaures": "<img src=\".\/jacketimg\/AAAS.jpg\" style=\"max-width: 100%\"> <\/ div>",
        "img1": "https://cdn.grofers.com/cdn-cgi/image/f=auto,fit=scale-down,q=70,metadata=none,w=1080/da/cms-assets/cms/product/f01e6727-a4a9-45fd-90a8-74617dc91e17.png",
        "img2": "https://cdn.grofers.com/cdn-cgi/image/f=auto,fit=scale-down,q=70,metadata=none,w=1080/da/cms-assets/cms/product/deb421f6-4c4d-4c65-9193-4be3a858c422.png",
        "img3": "https://cdn.grofers.com/cdn-cgi/image/f=auto,fit=scale-down,q=70,metadata=none,w=1080/da/cms-assets/cms/product/9de14f2c-b4be-4635-960c-3d863e472dac.png",
        "img4": "https://cdn.grofers.com/cdn-cgi/image/f=auto,fit=scale-down,q=70,metadata=none,w=1080/da/cms-assets/cms/product/f01e6727-a4a9-45fd-90a8-74617dc91e17.png",
        "img5": "https://cdn.grofers.com/cdn-cgi/image/f=auto,fit=scale-down,q=70,metadata=none,w=1080/da/cms-assets/cms/product/f01e6727-a4a9-45fd-90a8-74617dc91e17.png",
        "disp_order": 0,
        "from_csv": "1",
        "created_at": "2025-05-28 12:30:33",
        "md5_id": "9aa54c11a25dd74acbc08a2ee92c590e",
        "verients": []
    },
      {
        "id": "11",
        "name": "₹500 Myntra E-Gift Card Instant Voucher",
        "color": "Default",
        "size": "Free Size",
        "storage": null,
        "selling_price": "1",
        "mrp": "500",
        "fetaures": "<img src=\".\/jacketimg\/AAAS.jpg\" style=\"max-width: 100%\"> <\/ div>",
        "img1": "https://cdn.grofers.com/cdn-cgi/image/f=auto,fit=scale-down,q=70,metadata=none,w=1080/da/cms-assets/cms/product/19c1b5bd-3348-4784-80a4-46c1570684f8.png",
        "img2": "https://cdn.grofers.com/cdn-cgi/image/f=auto,fit=scale-down,q=70,metadata=none,w=1080/da/cms-assets/cms/product/deb421f6-4c4d-4c65-9193-4be3a858c422.png",
        "img3": "https://cdn.grofers.com/cdn-cgi/image/f=auto,fit=scale-down,q=70,metadata=none,w=1080/da/cms-assets/cms/product/9de14f2c-b4be-4635-960c-3d863e472dac.png",
        "img4": "https://cdn.grofers.com/cdn-cgi/image/f=auto,fit=scale-down,q=70,metadata=none,w=1080/da/cms-assets/cms/product/19c1b5bd-3348-4784-80a4-46c1570684f8.png",
        "img5": "https://cdn.grofers.com/cdn-cgi/image/f=auto,fit=scale-down,q=70,metadata=none,w=1080/da/cms-assets/cms/product/19c1b5bd-3348-4784-80a4-46c1570684f8.png",
        "disp_order": 0,
        "from_csv": "1",
        "created_at": "2025-05-28 12:30:33",
        "md5_id": "9aa54c11a25dd74acbc08a2ee92c590e",
        "verients": []
    },
    {
        "id": "20",
        "name": "₹500 Skechers E-Gift Card Instant Voucher",
        "color": "Default",
        "size": "Free Size",
        "storage": null,
        "selling_price": "1",
        "mrp": "500",
        "fetaures": "<img src=\".\/jacketimg\/AAAS.jpg\" style=\"max-width: 100%\"> <\/ div>",
        "img1": "https://cdn.grofers.com/cdn-cgi/image/f=auto,fit=scale-down,q=70,metadata=none,w=720/da/cms-assets/cms/product/b02d18bf-1475-4706-8af1-f7399715bd54.png",
        "img2": "https://cdn.grofers.com/cdn-cgi/image/f=auto,fit=scale-down,q=70,metadata=none,w=720/da/cms-assets/cms/product/5ae8f1b6-b1f0-484d-bfa2-b612b520e7f3.png",
        "img3": "",
        "img4": "",
        "img5": "",
        "disp_order": 0,
        "from_csv": "1",
        "created_at": "2025-05-28 12:01:15",
        "md5_id": "a6a9f2e63a9968b3e723e77cbffccde0",
        "verients": []
    },
      {
        "id": "12",
        "name": "₹500 Campus E-Gift Card Instant Voucher",
        "color": "Default",
        "size": "Free Size",
        "storage": null,
        "selling_price": "1",
        "mrp": "500",
        "fetaures": "<img src=\".\/jacketimg\/AAAS.jpg\" style=\"max-width: 100%\"> <\/ div>",
        "img1": "https://cdn.grofers.com/cdn-cgi/image/f=auto,fit=scale-down,q=70,metadata=none,w=1080/da/cms-assets/cms/product/f872c026-0ee6-4c26-9427-8b5164c21a4e.png",
        "img2": "https://cdn.grofers.com/cdn-cgi/image/f=auto,fit=scale-down,q=70,metadata=none,w=1080/da/cms-assets/cms/product/deb421f6-4c4d-4c65-9193-4be3a858c422.png",
        "img3": "https://cdn.grofers.com/cdn-cgi/image/f=auto,fit=scale-down,q=70,metadata=none,w=1080/da/cms-assets/cms/product/9de14f2c-b4be-4635-960c-3d863e472dac.png",
        "img4": "https://cdn.grofers.com/cdn-cgi/image/f=auto,fit=scale-down,q=70,metadata=none,w=1080/da/cms-assets/cms/product/f872c026-0ee6-4c26-9427-8b5164c21a4e.png",
        "img5": "https://cdn.grofers.com/cdn-cgi/image/f=auto,fit=scale-down,q=70,metadata=none,w=1080/da/cms-assets/cms/product/f872c026-0ee6-4c26-9427-8b5164c21a4e.png",
        "disp_order": 0,
        "from_csv": "1",
        "created_at": "2025-05-28 12:30:33",
        "md5_id": "9aa54c11a25dd74acbc08a2ee92c590e",
        "verients": []
    }
]
